MateGenT1/__init__.py
MateGenT1/baseTools.py
MateGenT1/getProfile.py
MateGenT1/mainFunc.py
MateGenT1/mateGenClass.py
MateGenT1-0.0.7.dist-info/METADATA
MateGenT1-0.0.7.dist-info/WHEEL
MateGenT1-0.0.7.dist-info/entry_points.txt
MateGenT1-0.0.7.dist-info/top_level.txt
MateGenT1-0.0.7.dist-info/RECORD
